[{
    "quote": "No one has ever become poor by giving",
    "author": "Anne Frank",
    "length": 37
  }, {
    "quote": "Everything has beauty but not everyone sees it",
    "author": "Confucius",
    "length": 46
  }, {
    "quote": "The mind is a wonderful servant but a terrible master",
    "author": "Robin Sharma",
    "length": 53
  }, {
    "quote": "Nothing will work unless you do",
    "author": "Maya Angelou",
    "length": 31
  }, {
    "quote": "Do not raise your voice improve your argument",
    "author": "Desmond Tutu",
    "length": 45
  }, {
    "quote": "Our lives are like a candle in the wind",
    "author": "Carl Sandburg",
    "length": 39
  }, {
    "quote": "Be a voice not an echo",
    "author": "Unknown",
    "length": 22
  }, {
    "quote": "The only way to have a friend is to be one",
    "author": "Ralph Waldo Emerson",
    "length": 42
  }, {
    "quote": "A friend is one who knows us but loves us anyway",
    "author": "Jerome Cummings",
    "length": 48
  }, {
    "quote": "Fate chooses our relatives We choose our friends",
    "author": "Jacques Delille",
    "length": 48
  }, {
    "quote": "A faithful friend is the medicine of life",
    "author": "Ecclesiasticus 6:16",
    "length": 41
  }, {
    "quote": "Impossible is for the unwilling",
    "author": "John Keats",
    "length": 31
  }, {
    "quote": "No pressure No diamonds",
    "author": "Thomas Carlyle",
    "length": 23
  }, {
    "quote": "My life is my message",
    "author": "Mahatma Gandhi",
    "length": 21
  }, {
    "quote": "My life is my argument",
    "author": "Albert Schweitzer",
    "length": 22
  }, {
    "quote": "Broken crayons still color",
    "author": "Unknown",
    "length": 26
  }, {
    "quote": "Whatever you are be a good one",
    "author": "Abraham Lincoln",
    "length": 30
  }, {
    "quote": "If it matters to you You will find a way",
    "author": "Charlie Gilkey",
    "length": 40
  }, {
    "quote": "Whatever you do Do with all your might",
    "author": "Marcus Tullius Cicero",
    "length": 38
  }, {
    "quote": "If you are going through hell Keep going",
    "author": "Winston Churchill",
    "length": 41
  }, {
    "quote": "We are twice armed if we fight with faith",
    "author": "Plato",
    "length": 41
  }, {
    "quote": "The wisest mind has something yet to learn",
    "author": "George Santanaya",
    "length": 42
  }, {
    "quote": "Persistence guarantees that results are inevitable",
    "author": "Paramahansa Yogananda",
    "length": 50
  }, {
    "quote": "In life you need either inspiration or desperation",
    "author": "Tony Robbins",
    "length": 50
  }, {
    "quote": "I would rather die on my feet than live on my knees",
    "author": "Euripides",
    "length": 51
  }, {
    "quote": "It does not matter how slowly you go as long as you do not stop",
    "author": "Confucius",
    "length": 63
  }, {
    "quote": "It is better to live one day as a lion than a thousand days as a lamb",
    "author": "Roman proverb",
    "length": 69
  }, {
    "quote": "The two most important days in your life are the day you are born and they day you find out why",
    "author": "Mark Twain",
    "length": 95
  }, {
    "quote": "Each day provides its own gifts",
    "author": "Marcus Aurelius",
    "length": 31
  }, {
    "quote": "Nothing is worth more than this day",
    "author": "Johann Wolfgang von Goethe",
    "length": 35
  }, {
    "quote": "Believe you can and you are halfway there",
    "author": "Theodore Roosevelt",
    "length": 41
  }, {
    "quote": "You make mistakes Mistakes do not make you",
    "author": "Unknown",
    "length": 42
  }, {
    "quote": "Do not go through life Grow through life",
    "author": "Eric Butterworth",
    "length": 41
  },
  {
    "quote": "What consumes your mind controls your life",
    "author": "Unknown",
    "length": 42
  },
  {
    "quote": "The time is always right to do what is right",
    "author": "Martin Luther King Jr.",
    "length": 44
  },
  {
    "quote": "May your choices reflect your hopes not your fears",
    "author": "Nelson Mandela",
    "length": 50
  },
  {
    "quote": "Tough times never last but tough people do",
    "author": "Robert H. Schiuller",
    "length": 42
  },
  {
    "quote": "Problems are not stop signs they are guidelines",
    "author": "Robert H. Schiuller",
    "length": 48
  },
  {
    "quote": "Dream as if you’ll live forever live as if you’ll die today",
    "author": "James Dean",
    "length": 60
  },
  {
    "quote": "Be yourself; everyone else is already taken",
    "author": "Oscar Wilde",
    "length": 43
  },
  {
    "quote": "You only live once, but if you do it right once is enough",
    "author": "Mae West",
    "length": 57
  },
  {
    "quote": "For every minute you are angry you lose sixty seconds of happiness",
    "author": "Ralph Waldo Emerson",
    "length": 66
  },
  {
    "quote": "If you can not explain it to a six year old you do not understand it yourself",
    "author": "Albert Einstein",
    "length": 77
  }

]